pascalvoc_to_image/__init__.py
pascalvoc_to_image-1.0.0.data/scripts/pascalvoc-to-image
pascalvoc_to_image-1.0.0.dist-info/METADATA
pascalvoc_to_image-1.0.0.dist-info/RECORD
pascalvoc_to_image-1.0.0.dist-info/WHEEL
pascalvoc_to_image-1.0.0.dist-info/top_level.txt
