Metadata-Version: 2.1
Name: pascalvoc-to-image
Version: 1.0.0
Summary: Tool to cut images from bounding boxes in PascalVOC XML files.
Home-page: http://www.gitlab.com/jdreg95/pascalvoc-to-image
Author: Jori Regter
Author-email: joriregter@gmail.com
License: GNU GPLv3
Platform: UNKNOWN
Requires-Dist: pillow (==5.1.0)
Requires-Dist: tqdm (==4.23.4)
